pert/PERT.py
pert/__init__.py
pertdist-0.1.2.dist-info/WHEEL
pertdist-0.1.2.dist-info/METADATA
pertdist-0.1.2.dist-info/RECORD
