Metadata-Version: 2.3
Name: pertdist
Version: 0.1.2
Summary: Add your description here
Requires-Dist: numpy>=2.4.0
Requires-Dist: pydantic>=2.12.5
Requires-Dist: scipy>=1.16.3
Requires-Python: >=3.11
